build/lib/flent/__init__.py
build/lib/flent/__main__.py
build/lib/flent/aggregators.py
build/lib/flent/batch.py
build/lib/flent/build_info.py
build/lib/flent/combiners.py
build/lib/flent/error_ellipse.py
build/lib/flent/flycheck_runners.py
build/lib/flent/formatters.py
build/lib/flent/gui.py
build/lib/flent/loggers.py
build/lib/flent/metadata.py
build/lib/flent/plotters.py
build/lib/flent/rcparser.py
build/lib/flent/resultset.py
build/lib/flent/runners.py
build/lib/flent/settings.py
build/lib/flent/tcp_info.py
build/lib/flent/testenv.py
build/lib/flent/transformers.py
build/lib/flent/util.py
data/exp/dumps/tcp-upload-compete/analyse-flows.py
doc/.gitignore
doc/Makefile
doc/conf.py
doc/contents.rst
doc/data-format.rst
doc/files.rst
doc/gui.rst
doc/intro.rst
doc/manpage.rst
doc/misc.rst
doc/options.rst
doc/output-formats.rst
doc/quickstart.rst
doc/short-intro.rst
doc/tests.rst
doc/_static/.gitignore
doc/_static/custom.css
doc/_static/flent-screenshot.png
doc/_templates/index.html
doc/_templates/layout.html
flent/__init__.py
flent/__main__.py
flent/aggregators.py
flent/batch.py
flent/build_info.py
flent/combiners.py
flent/error_ellipse.py
flent/flycheck_runners.py
flent/formatters.py
flent/gui.py
flent/loggers.py
flent/metadata.py
flent/plotters.py
flent/rcparser.py
flent/resultset.py
flent/runners.py
flent/settings.py
flent/tcp_info.py
flent/testenv.py
flent/transformers.py
flent/util.py
flent/scripts/dash_client.sh
flent/scripts/netstat_iterate.sh
flent/scripts/ss_iterate.sh
flent/scripts/stat_iterate.sh
flent/scripts/tc_iterate.sh
flent/scripts/wifistats_iterate.sh
flent/tests/bursts.conf
flent/tests/bursts_11e.conf
flent/tests/cisco_5tcpup.conf
flent/tests/cisco_5tcpup_2udpflood.conf
flent/tests/common.inc
flent/tests/cpu_stats.inc
flent/tests/cubic_bbr.conf
flent/tests/cubic_cdg.conf
flent/tests/cubic_dctcp.conf
flent/tests/cubic_ledbat.conf
flent/tests/cubic_ledbat_1.conf
flent/tests/cubic_reno.conf
flent/tests/cubic_westwood.conf
flent/tests/dash_mixin.inc
flent-2.2.0.dist-info/LICENSE
flent-2.2.0.dist-info/METADATA
flent-2.2.0.dist-info/WHEEL
flent-2.2.0.dist-info/entry_points.txt
flent-2.2.0.dist-info/top_level.txt
flent-2.2.0.dist-info/RECORD
