Metadata-Version: 2.1
Name: flent
Version: 2.2.0
Summary: The FLExible Network Tester
Home-page: http://flent.org
Author: Toke Høiland-Jørgensen <toke@toke.dk>
Author-email: toke@toke.dk
License: GNU GPLv3
Classifier: Development Status :: 5 - Production/Stable
Classifier: Environment :: Console
Classifier: Environment :: MacOS X
Classifier: Environment :: X11 Applications
Classifier: Environment :: X11 Applications :: Qt
Classifier: Intended Audience :: Developers
Classifier: Intended Audience :: Education
Classifier: Intended Audience :: Science/Research
Classifier: Intended Audience :: System Administrators
Classifier: Intended Audience :: Telecommunications Industry
Classifier: License :: OSI Approved :: GNU General Public License v3 or later (GPLv3+)
Classifier: Operating System :: MacOS :: MacOS X
Classifier: Operating System :: POSIX
Classifier: Programming Language :: Python
Classifier: Programming Language :: Python :: 3
Classifier: Programming Language :: Python :: 3.6
Classifier: Programming Language :: Python :: 3.7
Classifier: Programming Language :: Python :: 3 :: Only
Classifier: Topic :: Internet
Classifier: Topic :: System :: Benchmark
Classifier: Topic :: System :: Networking
Classifier: Topic :: Utilities
License-File: LICENSE
Provides-Extra: gui
Requires-Dist: QtPy; extra == "gui"
Requires-Dist: PyQt5; extra == "gui"
Provides-Extra: plots
Requires-Dist: matplotlib>=1.5; extra == "plots"
